ds78/__init__.py
ds78/main.py
ds78/utils.py
ds78/video_duration.py
ds78-0.0.8.dist-info/METADATA
ds78-0.0.8.dist-info/WHEEL
ds78-0.0.8.dist-info/entry_points.txt
ds78-0.0.8.dist-info/RECORD
