Metadata-Version: 2.1
Name: ds78
Version: 0.0.8
Summary: 
Author: Dmitry Drozdov
Author-email: dinochrom1@gmail.com
Requires-Python: >=3.10,<4.0
Classifier: Programming Language :: Python :: 3
Classifier: Programming Language :: Python :: 3.10
Classifier: Programming Language :: Python :: 3.11
Requires-Dist: tqdm (>=4.65.0,<5.0.0)
Requires-Dist: typer[all] (>=0.7.0,<0.8.0)
